{"nome":"Usuário","email":"user@gmail.com","senha":"123456","dicaDeSenha":"dica","status":true,"contas":[{"cor":{"name":"","value":"","valid":true},"nome":{"name":"","value":"twrtewrwr","valid":true},"saldoPrevisto":{"name":"","value":100.0,"valid":true},"saldoAtual":{"name":"","value":90.0,"valid":true}}],"categorias":[],"transacoes":[{"tipoTransacao":"DESPESA","data":"03/09/2014","recorrencia":"MENSAL","descricao":"rerewewr","conta":"twrtewrwr","repeticao":0,"ocorrencias":0,"dia_semana":0,"dia_mes":0,"fixo":false,"corTransacao":{"name":"","value":"","valid":true},"nomeTransacao":{"name":"","value":"aaaa","valid":true},"categoriaTransacao":{"name":"","value":"Saúde","valid":true},"saldoAtualTransacao":{"name":"","value":10.0,"valid":true},"saldoPrevistoTransacao":{"name":"","value":10.0,"valid":true}}]}